[
  {
    "regexp": "^(?:\\/(_next\\/data\\/[^/]{1,}))?\\/dashboard(?:\\/((?:[^\\/#\\?]+?)(?:\\/(?:[^\\/#\\?]+?))*))?(\\\\.json)?[\\/#\\?]?$",
    "originalSource": "/dashboard/:path*"
  },
  {
    "regexp": "^(?:\\/(_next\\/data\\/[^/]{1,}))?\\/organization(?:\\/((?:[^\\/#\\?]+?)(?:\\/(?:[^\\/#\\?]+?))*))?(\\\\.json)?[\\/#\\?]?$",
    "originalSource": "/organization/:path*"
  },
  {
    "regexp": "^(?:\\/(_next\\/data\\/[^/]{1,}))?\\/events(?:\\/((?:[^\\/#\\?]+?)(?:\\/(?:[^\\/#\\?]+?))*))?(\\\\.json)?[\\/#\\?]?$",
    "originalSource": "/events/:path*"
  },
  {
    "regexp": "^(?:\\/(_next\\/data\\/[^/]{1,}))?\\/auth(?:\\/((?:[^\\/#\\?]+?)(?:\\/(?:[^\\/#\\?]+?))*))?(\\\\.json)?[\\/#\\?]?$",
    "originalSource": "/auth/:path*"
  }
]